LICENSE
README.md
setup.cfg
setup.py
horuz/__init__.py
horuz/cli.py
horuz.egg-info/PKG-INFO
horuz.egg-info/SOURCES.txt
horuz.egg-info/dependency_links.txt
horuz.egg-info/entry_points.txt
horuz.egg-info/requires.txt
horuz.egg-info/top_level.txt
horuz/commands/__init__.py
horuz/commands/cmd_collect.py
horuz/commands/cmd_config.py
horuz/commands/cmd_projects.py
horuz/commands/cmd_search.py
horuz/commands/cmd_sessions.py
horuz/utils/__init__.py
horuz/utils/cli.py
horuz/utils/es.py
horuz/utils/files.py
horuz/utils/formatting.py
horuz/utils/generators.py
horuz/utils/style.py