Metadata-Version: 2.1
Name: horuz
Version: 0.0.7
Summary: Save and query your recon data on ElasticSearch.
Home-page: https://horuz.misalabs.com
Author: Misa G.
Author-email: hi@misalabs.com
Maintainer: Misa G.
Maintainer-email: hi@misalabs.com
License: MIT license
Keywords: recon,elasticsearch
Platform: UNKNOWN
Classifier: Development Status :: 3 - Alpha
Classifier: Intended Audience :: Developers
Classifier: Topic :: Software Development :: Build Tools
Classifier: License :: OSI Approved :: MIT License
Classifier: Programming Language :: Python :: 3
Classifier: Programming Language :: Python :: 3.4
Classifier: Programming Language :: Python :: 3.5
Classifier: Programming Language :: Python :: 3.6
Classifier: Programming Language :: Python :: 3.7
Classifier: Programming Language :: Python :: 3.9
License-File: LICENSE
